{
	"autoFocus": {
		"description": "get focus when component mounted",
		"optionType": "boolean",
		"defaultValue": "false"
	},
	"checked": {
		"description": "Specifies whether the checkbox is selected.",
		"optionType": "boolean",
		"defaultValue": "false"
	},
	"defaultChecked": {
		"description": "Specifies the initial state: whether or not the checkbox is selected.",
		"optionType": "boolean",
		"defaultValue": "false"
	},
	"disabled": {
		"description": "Disable checkbox",
		"optionType": "boolean",
		"defaultValue": "false"
	},
	"indeterminate": {
		"description": "indeterminate checked state of checkbox",
		"optionType": "boolean",
		"defaultValue": "false"
	}
}